{
    "resources": [
      {
        "asset_id": "f90dfeccea89ba13535f781db8b5a4bf",
        "public_id": "small_event6_e258176262",
        "format": "jpg",
        "version": 1621390960,
        "resource_type": "image",
        "type": "upload",
        "created_at": "2021-05-19T02:22:40Z",
        "bytes": 30404,
        "width": 500,
        "height": 333,
        "url": "http://res.cloudinary.com/dm1ukioyd/image/upload/v1621390960/small_event6_e258176262.jpg",
        "secure_url": "https://res.cloudinary.com/dm1ukioyd/image/upload/v1621390960/small_event6_e258176262.jpg"
      },
      {
        "asset_id": "ac3ab9402ef117594c4267b2dd39e092",
        "public_id": "medium_event6_e258176262",
        "format": "jpg",
        "version": 1621390959,
        "resource_type": "image",
        "type": "upload",
        "created_at": "2021-05-19T02:22:39Z",
        "bytes": 55843,
        "width": 750,
        "height": 500,
        "url": "http://res.cloudinary.com/dm1ukioyd/image/upload/v1621390959/medium_event6_e258176262.jpg",
        "secure_url": "https://res.cloudinary.com/dm1ukioyd/image/upload/v1621390959/medium_event6_e258176262.jpg"
      },
      {
        "asset_id": "d3dc608a53e70e64e3394c00bcd0da63",
        "public_id": "large_event6_e258176262",
        "format": "jpg",
        "version": 1621390958,
        "resource_type": "image",
        "type": "upload",
        "created_at": "2021-05-19T02:22:38Z",
        "bytes": 90787,
        "width": 1000,
        "height": 667,
        "url": "http://res.cloudinary.com/dm1ukioyd/image/upload/v1621390958/large_event6_e258176262.jpg",
        "secure_url": "https://res.cloudinary.com/dm1ukioyd/image/upload/v1621390958/large_event6_e258176262.jpg"
      },
      {
        "asset_id": "8c76b67fa7a3e51f2a28e2b14231e3a1",
        "public_id": "thumbnail_event6_e258176262",
        "format": "jpg",
        "version": 1621390957,
        "resource_type": "image",
        "type": "upload",
        "created_at": "2021-05-19T02:22:37Z",
        "bytes": 9763,
        "width": 234,
        "height": 156,
        "url": "http://res.cloudinary.com/dm1ukioyd/image/upload/v1621390957/thumbnail_event6_e258176262.jpg",
        "secure_url": "https://res.cloudinary.com/dm1ukioyd/image/upload/v1621390957/thumbnail_event6_e258176262.jpg"
      },
      {
        "asset_id": "4fa7a1414e54667d5e7c1b1fe07f2b2c",
        "public_id": "event6_e258176262",
        "format": "jpg",
        "version": 1621390956,
        "resource_type": "image",
        "type": "upload",
        "created_at": "2021-05-19T02:22:36Z",
        "bytes": 368116,
        "width": 1920,
        "height": 1280,
        "url": "http://res.cloudinary.com/dm1ukioyd/image/upload/v1621390956/event6_e258176262.jpg",
        "secure_url": "https://res.cloudinary.com/dm1ukioyd/image/upload/v1621390956/event6_e258176262.jpg"
      },
      {
        "asset_id": "95393e437eaa6e47850e998fa91141d2",
        "public_id": "small_event6_edc2c60b7d",
        "format": "jpg",
        "version": 1620183411,
        "resource_type": "image",
        "type": "upload",
        "created_at": "2021-05-05T02:56:51Z",
        "bytes": 30404,
        "width": 500,
        "height": 333,
        "url": "http://res.cloudinary.com/dm1ukioyd/image/upload/v1620183411/small_event6_edc2c60b7d.jpg",
        "secure_url": "https://res.cloudinary.com/dm1ukioyd/image/upload/v1620183411/small_event6_edc2c60b7d.jpg"
      },
      {
        "asset_id": "9303c264fcfe93fd89f4036b6794c759",
        "public_id": "medium_event6_edc2c60b7d",
        "format": "jpg",
        "version": 1620183411,
        "resource_type": "image",
        "type": "upload",
        "created_at": "2021-05-05T02:56:51Z",
        "bytes": 55843,
        "width": 750,
        "height": 500,
        "url": "http://res.cloudinary.com/dm1ukioyd/image/upload/v1620183411/medium_event6_edc2c60b7d.jpg",
        "secure_url": "https://res.cloudinary.com/dm1ukioyd/image/upload/v1620183411/medium_event6_edc2c60b7d.jpg"
      },
      {
        "asset_id": "36302788475810f9234b54c3d68141a1",
        "public_id": "small_event5_59e2b982a9",
        "format": "jpg",
        "version": 1620183411,
        "resource_type": "image",
        "type": "upload",
        "created_at": "2021-05-05T02:56:51Z",
        "bytes": 28271,
        "width": 500,
        "height": 335,
        "url": "http://res.cloudinary.com/dm1ukioyd/image/upload/v1620183411/small_event5_59e2b982a9.jpg",
        "secure_url": "https://res.cloudinary.com/dm1ukioyd/image/upload/v1620183411/small_event5_59e2b982a9.jpg"
      },
      {
        "asset_id": "ce08e7ae6371d63aa41c74b384f9d205",
        "public_id": "medium_event5_59e2b982a9",
        "format": "jpg",
        "version": 1620183410,
        "resource_type": "image",
        "type": "upload",
        "created_at": "2021-05-05T02:56:50Z",
        "bytes": 51346,
        "width": 750,
        "height": 502,
        "url": "http://res.cloudinary.com/dm1ukioyd/image/upload/v1620183410/medium_event5_59e2b982a9.jpg",
        "secure_url": "https://res.cloudinary.com/dm1ukioyd/image/upload/v1620183410/medium_event5_59e2b982a9.jpg"
      },
      {
        "asset_id": "bc344b3f5313bb211a2558f56ab05abd",
        "public_id": "large_event6_edc2c60b7d",
        "format": "jpg",
        "version": 1620183410,
        "resource_type": "image",
        "type": "upload",
        "created_at": "2021-05-05T02:56:50Z",
        "bytes": 90787,
        "width": 1000,
        "height": 667,
        "url": "http://res.cloudinary.com/dm1ukioyd/image/upload/v1620183410/large_event6_edc2c60b7d.jpg",
        "secure_url": "https://res.cloudinary.com/dm1ukioyd/image/upload/v1620183410/large_event6_edc2c60b7d.jpg"
      }
    ],
    "next_cursor": "f6f24a55f54bca990562047d832c8a6fe5cea35697d6539bf87eaf23016200c9"
  }